python_deenair_sdk/__init__.py
python_deenair_sdk/core.py
python_deenair_sdk/requesters/__init__.py
python_deenair_sdk/requesters/base.py
python_deenair_sdk/requesters/core.py
python_deenair_sdk/requesters/http.py
python_deenair_sdk-0.0.9.dist-info/METADATA
python_deenair_sdk-0.0.9.dist-info/WHEEL
python_deenair_sdk-0.0.9.dist-info/top_level.txt
python_deenair_sdk-0.0.9.dist-info/RECORD
