Metadata-Version: 2.1
Name: python-deenair-sdk
Version: 0.0.9
Summary: pythod-deenair-sdk. Base python library to interact with DeenAiR blockchain.
Home-page: https://github.com/deenair-labs/python_deenair_sdk
Author: DeenAiR Labs
Author-email: social@deenair.org
License: MIT
Keywords: DeenAiR
Classifier: Development Status :: 3 - Alpha
Classifier: License :: OSI Approved :: MIT License
Classifier: Programming Language :: Python :: 3
Classifier: Programming Language :: Python :: 3.7
Classifier: Programming Language :: Python :: 3.8
Classifier: Programming Language :: Python :: 3.9
Classifier: Programming Language :: Python :: 3.10
Requires-Python: >=3.7, <4
Requires-Dist: base58 (~=2.1.1)
Requires-Dist: requests (~=2.28.1)
Requires-Dist: bip-utils
Requires-Dist: mnemonic
Requires-Dist: setuptools
Requires-Dist: python-dateutil
Requires-Dist: pynacl (==1.5.0)
